ontoloviz/__init__.py
ontoloviz/__main__.py
ontoloviz/app.py
ontoloviz/app_test.py
ontoloviz/app_utils.py
ontoloviz/core.py
ontoloviz/core_utils.py
ontoloviz/obo_utils.py
ontoloviz/web.py
ontoloviz/assets/logo.svg
ontoloviz/assets/scripts.js
ontoloviz/assets/style.css
ontoloviz/assets/tooltip.js
ontoloviz-2.0.2.dist-info/licenses/LICENSE
ontoloviz-2.0.2.dist-info/METADATA
ontoloviz-2.0.2.dist-info/WHEEL
ontoloviz-2.0.2.dist-info/entry_points.txt
ontoloviz-2.0.2.dist-info/top_level.txt
ontoloviz-2.0.2.dist-info/RECORD
