Metadata-Version: 2.4
Name: ontoloviz
Version: 2.0.2
Summary: OntoloViz drug- and phenotype-ontology visualization GUI
Author-email: Matthias Ley <matthias.ley@delta4.ai>
License-Expression: MIT
Project-URL: Repository, https://github.com/Delta4AI/OntoloViz
Project-URL: Bug Tracker, https://github.com/Delta4AI/OntoloViz/issues
Project-URL: Releases, https://github.com/Delta4AI/OntoloViz/releases
Keywords: MeSH,ATC,ontology,visualization,sunburst,drug,phenotype,GUI
Classifier: Operating System :: OS Independent
Classifier: Programming Language :: Python :: 3 :: Only
Classifier: Programming Language :: Python :: 3.9
Classifier: Programming Language :: Python :: 3.10
Classifier: Programming Language :: Python :: 3.11
Classifier: Programming Language :: Python :: 3.12
Classifier: Topic :: Software Development :: Libraries :: Python Modules
Classifier: Operating System :: OS Independent
Requires-Python: <4.0,>=3.9
License-File: LICENSE
Requires-Dist: plotly>=5.15.0
Requires-Dist: openpyxl>=3.1.2
Requires-Dist: packaging>=23.0
Requires-Dist: requests>=2.31.0
Provides-Extra: web
Requires-Dist: dash>=3.0.3; extra == "web"
Requires-Dist: dash-bootstrap-components>=2.0.1; extra == "web"
Requires-Dist: pandas>=2.2.3; extra == "web"
Dynamic: license-file
